yaz_scripting_plugin-0.0.4.dist-info/WHEEL
yaz_scripting_plugin-0.0.4.dist-info/RECORD
yaz_scripting_plugin-0.0.4.dist-info/METADATA
yaz_scripting_plugin-0.0.4.dist-info/top_level.txt
yaz_scripting_plugin-0.0.4.dist-info/DESCRIPTION.rst
yaz_scripting_plugin-0.0.4.dist-info/metadata.json
yaz_scripting_plugin-0.0.4.data/scripts/yaz-screen-wrapper
yaz_scripting_plugin-0.0.4.data/scripts/yaz-scripting
yaz_scripting_plugin/error.py
yaz_scripting_plugin/shell.py
yaz_scripting_plugin/log.py
yaz_scripting_plugin/__init__.py
yaz_scripting_plugin/version.py
