Metadata-Version: 2.0
Name: yaz-scripting-plugin
Version: 0.0.4
Summary: A plugin for YAZ providing shell scripting access
Home-page: https://github.com/yaz/yaz_scripting_plugin
Author: Boudewijn Schoon
Author-email: yaz@frayja.com
License: MIT
Platform: UNKNOWN
Classifier: Development Status :: 4 - Beta
Classifier: Environment :: Console
Classifier: License :: OSI Approved :: MIT License
Classifier: Programming Language :: Python :: 3.5
Classifier: Programming Language :: Python :: 3.6
Requires-Dist: yaz
Requires-Dist: yaz-templating-plugin
